{
  "id": "dropdown_menu",
  "type": "SharedSlice",
  "name": "DropdownMenu",
  "description": "DropdownMenu",
  "variations": [
    {
      "id": "default",
      "name": "Default",
      "docURL": "...",
      "version": "sktwi1xtmkfgx8626",
      "description": "DropdownMenu",
      "primary": {
        "title": {
          "type": "StructuredText",
          "config": {
            "label": "Title",
            "placeholder": "This is where it all begins...",
            "allowTargetBlank": true,
            "single": "paragraph"
          }
        }
      },
      "items": {
        "subMenuTitle": {
          "type": "StructuredText",
          "config": {
            "label": "Sub Menu title",
            "placeholder": "",
            "allowTargetBlank": true,
            "single": "heading3"
          }
        },
        "linkTitle": {
          "type": "StructuredText",
          "config": {
            "label": "Link Title",
            "placeholder": "",
            "allowTargetBlank": true,
            "single": "paragraph,preformatted,heading1,heading2,heading3,heading4,heading5,heading6,strong,em,hyperlink,image,embed,list-item,o-list-item,rtl"
          }
        }
      },
      "imageUrl": "https://images.prismic.io/slice-machine/621a5ec4-0387-4bc5-9860-2dd46cbc07cd_default_ss.png?auto=compress,format"
    }
  ]
}